LICENSE.txt
MANIFEST.in
README.md
requirements.txt
setup.cfg
setup.py
mechanic/VERSION
mechanic/__init__.py
mechanic/exceptions.py
mechanic/fields.py
mechanic/main.py
mechanic/openapi.py
mechanic/utils.py
mechanic/__pycache__/__init__.cpython-36.pyc
mechanic/__pycache__/exceptions.cpython-36.pyc
mechanic/__pycache__/fields.cpython-36.pyc
mechanic/__pycache__/main.cpython-36.pyc
mechanic/__pycache__/openapi.cpython-36.pyc
mechanic/__pycache__/utils.cpython-36.pyc
mechanic/src/__init__.py
mechanic/src/merger.py
mechanic/src/__pycache__/__init__.cpython-36.pyc
mechanic/src/__pycache__/compiler.cpython-36.pyc
mechanic/src/__pycache__/generator.cpython-36.pyc
mechanic/src/__pycache__/merger.cpython-36.pyc
mechanic/src/__pycache__/reader.cpython-36.pyc
mechanic/src/__pycache__/utils.cpython-36.pyc
mechanic/static/swagger-ui-bundle.js
mechanic/static/swagger-ui-standalone-preset.js
mechanic/static/swagger-ui.css
mechanic/static/swagger/swagger-ui-bundle.js
mechanic/static/swagger/swagger-ui-bundle.js.map
mechanic/static/swagger/swagger-ui-index.html
mechanic/static/swagger/swagger-ui-standalone-preset.js
mechanic/static/swagger/swagger-ui-standalone-preset.js.map
mechanic/static/swagger/swagger-ui.css.map
mechanic/static/swagger/theme-faction.css
mechanic/static/swagger/theme-feeling-blue.css
mechanic/static/swagger/theme-flattop.css
mechanic/static/swagger/theme-material.css
mechanic/static/swagger/theme-monokai.css
mechanic/static/swagger/theme-muted.css
mechanic/static/swagger/theme-newspaper.css
mechanic/static/swagger/theme-outline.css
mechanic/static/swagger/theme-swagger-ui.css
mechanic/templates/code.tpl
mechanic/templates/swagger-ui-index.html
mechanic/templates/test.tpl
mechanic/templates/scaffold/default/.gitignore.tpl
mechanic/templates/scaffold/default/Dockerfile.tpl
mechanic/templates/scaffold/default/MANIFEST.in.tpl
mechanic/templates/scaffold/default/README.md.tpl
mechanic/templates/scaffold/default/requirements.txt.tpl
mechanic_gen.egg-info/PKG-INFO
mechanic_gen.egg-info/SOURCES.txt
mechanic_gen.egg-info/dependency_links.txt
mechanic_gen.egg-info/entry_points.txt
mechanic_gen.egg-info/requires.txt
mechanic_gen.egg-info/top_level.txt