Metadata-Version: 1.1
Name: mechanic-gen
Version: 1.6.0
Summary: Generates python code from the controller layer to the DB layer from an OpenAPI specification file.
Home-page: https://github.com/factioninc/mechanic
Author: Zack Schrag
Author-email: zack.schrag@factioninc.com
License: Mozilla Public License 2.0 (MPL 2.0)
Download-URL: https://github.com/factioninc/mechanic/archive/1.6.0.tar.gz
Keywords: openapi,api,generation
Platform: UNKNOWN
Classifier: Development Status :: 3 - Alpha
Classifier: Intended Audience :: Developers
Classifier: Topic :: Software Development :: Code Generators
Classifier: License :: OSI Approved :: Mozilla Public License 2.0 (MPL 2.0)
Classifier: Programming Language :: Python :: 3.6
